{"Tweet0": {"views": 16, "imgs": {"img0": "https://pbs.twimg.com/media/GCPADhla0AAAQV3?format=jpg&name=large", "img1": "https://pbs.twimg.com/media/GCPADhlaMAAZZgI?format=jpg&name=large"}}, "Tweet1": {"views": 94, "imgs": {"img0": "https://pbs.twimg.com/media/GCO6fu8aEAAgMs1?format=jpg&name=large"}}, "Tweet2": {"reposts": 6, "likes": 38, "bookmark": 1, "views": 274, "imgs": {"img0": "https://pbs.twimg.com/media/GCOcy5LboAAhXTN?format=jpg&name=large"}}, "Tweet3": {"like": 1, "views": 66, "imgs": {"img0": "https://pbs.twimg.com/media/GCOxA-IbkAAnM_-?format=jpg&name=large", "img1": "https://pbs.twimg.com/media/GCOxA-LbEAAdiH5?format=jpg&name=large", "img2": "https://pbs.twimg.com/media/GCOxA-Ka0AApjdW?format=jpg&name=large"}}, "Tweet4": {"reposts": 4, "likes": 11, "views": 152, "imgs": {"img0": "https://pbs.twimg.com/media/GCOccwGW8AAaa3Q?format=jpg&name=large", "img1": "https://pbs.twimg.com/media/GCOccwFXEAA04xz?format=jpg&name=large"}}, "Tweet5": {"reply": 1, "reposts": 4, "likes": 13, "views": 149, "imgs": {"img0": "https://pbs.twimg.com/media/GCOVKmpWoAAuXuy?format=jpg&name=large"}}, "Tweet6": {"reposts": 4, "likes": 8, "views": 119, "imgs": {"img0": "https://pbs.twimg.com/media/GCNuxMMXwAA9z61?format=jpg&name=large"}}, "Tweet7": {"reply": 1, "reposts": 10, "likes": 18, "views": 446, "imgs": {"img0": "https://pbs.twimg.com/media/GCNnUCgaQAAVgyF?format=jpg&name=large"}}, "Tweet8": {"reposts": 7, "likes": 18, "views": 308, "imgs": {"img0": "https://pbs.twimg.com/media/GCNA8N7bcAAkH-H?format=jpg&name=large"}}, "Tweet9": {"reply": 1, "views": 138, "imgs": {"img0": "https://pbs.twimg.com/media/GCNAtTNWgAETmoR?format=jpg&name=large", "img1": "https://pbs.twimg.com/media/GCNAt1tXAAAuavN?format=jpg&name=large"}}, "Tweet10": {"reposts": 70, "likes": 183, "bookmarks": 9, "views": 3214, "imgs": {"img0": "https://pbs.twimg.com/media/GCM8nnDagAALSrV?format=jpg&name=large"}}, "Tweet11": {"reposts": 13, "likes": 30, "bookmarks": 3, "views": 1853, "imgs": {"img0": "https://pbs.twimg.com/media/GCLOJfqakAEqdsI?format=jpg&name=large", "img1": "https://pbs.twimg.com/media/GApKQGdaAAA-oSf?format=jpg&name=large", "img2": "https://pbs.twimg.com/media/GApKL89b0AAYtu9?format=jpg&name=large", "img3": "https://pbs.twimg.com/media/GApKPcEbcAAeKj2?format=jpg&name=large"}}, "Tweet12": {"reposts": 89, "likes": 351, "bookmarks": 7, "views": 4985, "imgs": {"img0": "https://pbs.twimg.com/media/GCM5RxjbEAAgb24?format=jpg&name=large"}}, "Tweet13": {"reposts": 27, "likes": 86, "bookmark": 1, "views": 1172, "imgs": {"img0": "https://pbs.twimg.com/media/GCM4LtfaQAAGdPZ?format=jpg&name=large"}}, "Tweet14": {"repost": 1, "like": 1, "views": 152, "imgs": {"img0": "https://pbs.twimg.com/media/GCM3bqRbIAAsGUw?format=jpg&name=large"}}, "Tweet15": {"replies": 2, "reposts": 10, "likes": 78, "bookmarks": 4, "views": 2109, "imgs": {"img0": "https://pbs.twimg.com/media/GCM1x5XboAAXpAr?format=jpg&name=large", "img1": "https://pbs.twimg.com/media/GCM1x5aagAA8rZn?format=jpg&name=large"}}, "Tweet16": {"reposts": 3, "likes": 17, "views": 330, "imgs": {"img0": "https://pbs.twimg.com/media/GCMwudZbwAA25ab?format=jpg&name=large"}}, "Tweet17": {"reposts": 13, "likes": 51, "views": 715, "imgs": {"img0": "https://pbs.twimg.com/media/GCMwq02bwAAo5PN?format=jpg&name=large"}}, "Tweet18": {"like": 1, "views": 442, "imgs": {"img0": "https://pbs.twimg.com/media/GBdHYuybUAA05Ch?format=jpg&name=large"}}, "Tweet19": {"reposts": 6, "likes": 22, "views": 364, "imgs": {"img0": "https://pbs.twimg.com/media/GCMugGPaUAAvHKl?format=jpg&name=large"}}, "Tweet20": {"reposts": 4, "likes": 16, "views": 360, "imgs": {"img0": "https://pbs.twimg.com/media/GCMticmbwAAdfu4?format=jpg&name=large"}}, "Tweet21": {"likes": 4, "views": 120, "imgs": {"img0": "https://pbs.twimg.com/media/GCMtUgEXQAA5HYp?format=jpg&name=large"}}, "Tweet22": {"reposts": 37, "likes": 148, "bookmarks": 5, "views": 2215, "imgs": {"img0": "https://pbs.twimg.com/media/GCMrEJ5aAAAeF-y?format=jpg&name=large"}}, "Tweet23": {"reply": 1, "reposts": 107, "likes": 404, "bookmarks": 16, "views": 5230, "imgs": {"img0": "https://pbs.twimg.com/media/GCMpCttagAAiYrU?format=jpg&name=large"}}, "Tweet24": {"views": 150, "imgs": {"img0": "https://pbs.twimg.com/media/GCL7NeUWkAAFgN2?format=jpg&name=large", "img1": "https://pbs.twimg.com/media/GCL7NeiXgAAxb5B?format=jpg&name=large"}}, "Tweet25": {"reposts": 95, "likes": 401, "bookmarks": 10, "views": 5607, "imgs": {"img0": "https://pbs.twimg.com/media/GCMmRYtbgAAQDA8?format=jpg&name=large"}}, "Tweet26": {"replies": 2, "reposts": 220, "likes": 715, "bookmarks": 30, "views": 9327, "imgs": {"img0": "https://pbs.twimg.com/media/GCMl1etbUAAvxNR?format=jpg&name=large"}}, "Tweet27": {"reply": 1, "reposts": 8, "likes": 39, "bookmark": 1, "views": 1455, "imgs": {"img0": "https://pbs.twimg.com/media/GCHW-0_aQAAuzoP?format=jpg&name=large"}}, "Tweet28": {"likes": 3, "views": 160, "imgs": {"img0": "https://pbs.twimg.com/media/GCMhflIa4AAYjzN?format=jpg&name=large"}}, "Tweet29": {"reposts": 8, "likes": 15, "views": 324, "imgs": {"img0": "https://pbs.twimg.com/media/GCMbp3PaQAA_fwK?format=jpg&name=large"}}, "Tweet30": {"reposts": 32, "likes": 133, "bookmarks": 6, "views": 1683, "imgs": {"img0": "https://pbs.twimg.com/media/GCMbFArbgAAlDs6?format=jpg&name=large"}}}